jupyter_ascend_theme/__init__.py
jupyter_ascend_theme/_version.py
jupyter_ascend_theme-0.16.0.data/data/share/jupyter/labextensions/jupyter_ascend_theme/build_log.json
jupyter_ascend_theme-0.16.0.data/data/share/jupyter/labextensions/jupyter_ascend_theme/package.json
jupyter_ascend_theme-0.16.0.data/data/share/jupyter/labextensions/jupyter_ascend_theme/static/0ec523bfe61f21fa95e1.png
jupyter_ascend_theme-0.16.0.data/data/share/jupyter/labextensions/jupyter_ascend_theme/static/8c3f1d75af7fe9a5cf2c.png
jupyter_ascend_theme-0.16.0.data/data/share/jupyter/labextensions/jupyter_ascend_theme/static/lib_index_js.c6373db979e1ba6fcd32.js
jupyter_ascend_theme-0.16.0.data/data/share/jupyter/labextensions/jupyter_ascend_theme/static/lib_index_js.c6373db979e1ba6fcd32.js.map
jupyter_ascend_theme-0.16.0.data/data/share/jupyter/labextensions/jupyter_ascend_theme/static/remoteEntry.92552352aa52767016fe.js
jupyter_ascend_theme-0.16.0.data/data/share/jupyter/labextensions/jupyter_ascend_theme/static/remoteEntry.92552352aa52767016fe.js.map
jupyter_ascend_theme-0.16.0.data/data/share/jupyter/labextensions/jupyter_ascend_theme/static/style.js
jupyter_ascend_theme-0.16.0.data/data/share/jupyter/labextensions/jupyter_ascend_theme/themes/jupyter_ascend_theme/index.css
jupyter_ascend_theme-0.16.0.data/data/share/jupyter/labextensions/jupyter_ascend_theme/themes/jupyter_ascend_theme/index.js
jupyter_ascend_theme-0.16.0.data/data/share/jupyter/labextensions/jupyter_ascend_theme/install.json
jupyter_ascend_theme-0.16.0.dist-info/METADATA
jupyter_ascend_theme-0.16.0.dist-info/WHEEL
jupyter_ascend_theme-0.16.0.dist-info/licenses/LICENSE
jupyter_ascend_theme-0.16.0.dist-info/RECORD
